pluk/__init__.py
pluk/api.py
pluk/cli.py
pluk/db.py
pluk/init_db.py
pluk/refs_ts.py
pluk/shim.py
pluk/worker.py
pluk/SQL_UTIL/operations.py
pluk-0.6.1.dist-info/licenses/LICENSE
pluk-0.6.1.dist-info/METADATA
pluk-0.6.1.dist-info/WHEEL
pluk-0.6.1.dist-info/entry_points.txt
pluk-0.6.1.dist-info/top_level.txt
pluk-0.6.1.dist-info/RECORD
