Metadata-Version: 2.4
Name: pluk
Version: 0.6.1
Summary: Symbol lookup / search engine CLI
Author-email: Justus Jones <Justus1274@gmail.com>
License-Expression: MIT
Keywords: symbol,search,cli,index,lookup
Requires-Python: >=3.11
License-File: LICENSE
Requires-Dist: requests>=2.31
Requires-Dist: redis>=5.0
Requires-Dist: colorama>=0.4
Provides-Extra: api
Requires-Dist: fastapi>=0.116; extra == "api"
Requires-Dist: uvicorn[standard]>=0.35; extra == "api"
Provides-Extra: worker
Requires-Dist: celery>=5.3; extra == "worker"
Requires-Dist: gitpython>=3.1; extra == "worker"
Provides-Extra: db
Requires-Dist: psycopg[binary,pool]>=3.1; extra == "db"
Provides-Extra: refs
Requires-Dist: tree-sitter<0.26,>=0.24; extra == "refs"
Requires-Dist: tree-sitter-language-pack>=0.6.0; extra == "refs"
Provides-Extra: test
Requires-Dist: pytest>=7.0; extra == "test"
Requires-Dist: httpx>=0.24; extra == "test"
Dynamic: license-file
